bareutils/__init__.py
bareutils/compression.py
bareutils/cookies.py
bareutils/dates/__init__.py
bareutils/dates/helpers.py
bareutils/dates/rfc_7231.py
bareutils/dates/rfc_850.py
bareutils/header.py
bareutils/py.typed
bareutils/response_code.py
bareutils/streaming.py
bareutils/unpacking.py
bareutils-4.0.2.dist-info/LICENSE
bareutils-4.0.2.dist-info/WHEEL
bareutils-4.0.2.dist-info/METADATA
bareutils-4.0.2.dist-info/RECORD
